bot_core/__init__.py
bot_core/backend_client.py
bot_core/backend_core/__init__.py
bot_core/backend_core/app.py
bot_core/backend_core/db.py
bot_core/backend_core/models.py
bot_core/base_bot.py
bot_core/base_handler/__init__.py
bot_core/base_handler/base_router.py
bot_core/bot_middlewares/__init__.py
bot_core/bot_middlewares/middleware.py
bot_core/menu_manager/__init__.py
bot_core/menu_manager/base.py
bot_core/menu_manager/manager.py
bot_core/menu_manager/middleware.py
bot_core/referrals.py
bot_core/repository_clients/__init__.py
bot_core/repository_clients/google_sheets/__init__.py
bot_core/repository_clients/google_sheets/client.py
bot_core/repository_clients/google_sheets/registry.py
bot_core/repository_clients/s3_client.py
bot_core/run_backend.py
bot_core/run_bot.py
telegram_bot_core-0.1.6.dist-info/METADATA
telegram_bot_core-0.1.6.dist-info/WHEEL
telegram_bot_core-0.1.6.dist-info/RECORD
