Metadata-Version: 2.1
Name: telegram-bot-core
Version: 0.1.6
Summary: Core utilities for Telegram bots (aiogram v3): menu manager, backend sync, clients.
License: MIT
Author: Your Name
Author-email: remanam@mail.ru
Requires-Python: >=3.12,<4.0
Classifier: License :: OSI Approved :: MIT License
Classifier: Programming Language :: Python :: 3
Classifier: Programming Language :: Python :: 3.12
Classifier: Programming Language :: Python :: 3.13
Provides-Extra: backend
Provides-Extra: s3
Provides-Extra: sheets
Requires-Dist: SQLAlchemy (>=2.0,<3.0) ; extra == "backend"
Requires-Dist: aiobotocore (==2.16.1) ; extra == "s3"
Requires-Dist: aiogram (>=3.0,<4.0)
Requires-Dist: alembic (>=1.13,<2.0) ; extra == "backend"
Requires-Dist: asyncpg (>=0.29,<1.0) ; extra == "backend"
Requires-Dist: fastapi (>=0.115,<1.0) ; extra == "backend"
Requires-Dist: fastcrud (>=0.19,<1.0) ; extra == "backend"
Requires-Dist: gspread (>=6.0,<7.0) ; extra == "sheets"
Requires-Dist: httpx (>=0.27,<1.0)
Requires-Dist: oauth2client (>=4.1.3,<5.0) ; extra == "sheets"
Requires-Dist: openpyxl (>=3.1,<4.0) ; extra == "sheets"
Requires-Dist: pandas (>=2.2,<3.0) ; extra == "sheets"
Requires-Dist: python-dotenv (>=1.0,<2.0)
Requires-Dist: uvicorn (>=0.30,<1.0) ; extra == "backend"
